__init__.py
ultra_piston/__init__.py
ultra_piston/errors.py
ultra_piston/http_clients.py
ultra_piston/models.py
ultra_piston/piston.py
ultra_piston-1.0.0.dist-info/licenses/LICENSE
ultra_piston-1.0.0.dist-info/METADATA
ultra_piston-1.0.0.dist-info/WHEEL
ultra_piston-1.0.0.dist-info/top_level.txt
ultra_piston-1.0.0.dist-info/RECORD
