Metadata-Version: 2.4
Name: ultra-piston
Version: 1.0.0
Summary: An all-in-one API wrapper for the Piston API in Python
Author-email: Jiggly Balls <jigglyballs9000@gmail.com>
Project-URL: Source, https://github.com/Jiggly-Balls/ultra-piston
Project-URL: Documentation, https://game-state.readthedocs.io/en/latest/index.html
Project-URL: Issues, https://github.com/Jiggly-Balls/ultra-piston/issues
Project-URL: Stars, https://github.com/Jiggly-Balls/ultra-piston/stargazers
Classifier: Development Status :: 5 - Production/Stable
Classifier: Framework :: Pydantic
Classifier: Framework :: Pydantic :: 2
Classifier: Framework :: Pytest
Classifier: Framework :: Sphinx
Classifier: Natural Language :: English
Classifier: Operating System :: MacOS
Classifier: Operating System :: Microsoft :: Windows
Classifier: Operating System :: POSIX
Classifier: Operating System :: Unix
Classifier: Programming Language :: Python
Classifier: Programming Language :: Python :: 3
Classifier: Programming Language :: Python :: 3.10
Classifier: Programming Language :: Python :: 3.11
Classifier: Programming Language :: Python :: 3.12
Classifier: Programming Language :: Python :: 3.13
Classifier: Topic :: Documentation :: Sphinx
Classifier: Topic :: Software Development :: Libraries
Classifier: Topic :: Text Processing :: Markup :: reStructuredText
Classifier: Topic :: Utilities
Classifier: Typing :: Typed
Requires-Python: >=3.11
License-File: LICENSE
Requires-Dist: aiocache>=0.12.3
Requires-Dist: httpx>=0.28.1
Requires-Dist: pydantic>=2.11.7
Dynamic: license-file
